starlink/hds.so
starlink/__init__.py
starlink/.libs/libz-83853723.so.1.2.3
starlink_pyhds-0.2.dist-info/WHEEL
starlink_pyhds-0.2.dist-info/top_level.txt
starlink_pyhds-0.2.dist-info/METADATA
starlink_pyhds-0.2.dist-info/RECORD
