Metadata-Version: 2.1
Name: starlink-pyhds
Version: 0.2
Summary: Python interface to the Starlink HDS library
Home-page: https://github.com/sfgraves/starlink-pyhds
Author: SF Graves
Author-email: s.graves@eaobservatory.org
License: GNU GPL v3
Platform: UNKNOWN
Classifier: Development Status :: 4 - Beta
Classifier: License :: OSI Approved :: GNU General Public License v3 or later (GPLv3+)
Classifier: Programming Language :: Python
Classifier: Programming Language :: C
Classifier: Topic :: Scientific/Engineering :: Astronomy
Requires-Dist: numpy
